cat/__init__.py
cat/cat.py
cat/catffi.py
cat/const.py
cat/container.py
cat/event.py
cat/heartbeat.py
cat/message.py
cat/metric.py
cat/sdk.py
cat/transaction.py
cat/utils.py
cat/version.py
cat/lib/darwin/libcatclient.dylib
cat/lib/linux-glibc/libcatclient.so
cat/lib/linux-musl-libc/libcatclient.so
cat_sdk-3.0.1.dist-info/METADATA
cat_sdk-3.0.1.dist-info/WHEEL
cat_sdk-3.0.1.dist-info/top_level.txt
cat_sdk-3.0.1.dist-info/RECORD
